{
    "id": 76,
    "hidden": true,
    "title": "Proton Pack",
    "date": "2021-11-01",
    "image": "proton_001.jpg",
    "blocks": [
        {
            "blockType": 2,
            "content": "proton_001.jpg"
        },
        {
            "blockType": 2,
            "content": "proton_002.jpg"
        },
        {
            "blockType": 2,
            "content": "proton_003.jpg"
        },
        {
            "blockType": 2,
            "content": "proton_004.jpg"
        },
        {
            "blockType": 2,
            "content": "proton_005.jpg"
        },
        {
            "blockType": 2,
            "content": "proton_006.jpg"
        },
        {
            "blockType": 2,
            "content": "proton_007.jpg"
        },
        {
            "blockType": 2,
            "content": "proton_008.jpg"
        },
        {
            "blockType": 2,
            "content": "proton_009.jpg"
        },
        {
            "blockType": 2,
            "content": "proton_010.jpg"
        },
        {
            "blockType": 2,
            "content": "proton_011.jpg"
        },
        {
            "blockType": 2,
            "content": "proton_012.jpg"
        },
        {
            "blockType": 2,
            "content": "proton_013.jpg"
        },
        {
            "blockType": 2,
            "content": "proton_014.jpg"
        },
        {
            "blockType": 2,
            "content": "proton_015.jpg"
        },
        {
            "blockType": 2,
            "content": "proton_016.jpg"
        },
        {
            "blockType": 2,
            "content": "proton_017.jpg"
        },
        {
            "blockType": 2,
            "content": "proton_018.jpg"
        },
        {
            "blockType": 2,
            "content": "proton_019.jpg"
        },
        {
            "blockType": 2,
            "content": "proton_020.jpg"
        },
        {
            "blockType": 2,
            "content": "proton_021.jpg"
        },
        {
            "blockType": 2,
            "content": "proton_022.jpg"
        },
        {
            "blockType": 2,
            "content": "proton_023.jpg"
        },
        {
            "blockType": 2,
            "content": "proton_024.jpg"
        },
        {
            "blockType": 2,
            "content": "proton_025.jpg"
        },
        {
            "blockType": 2,
            "content": "proton_026.jpg"
        },
        {
            "blockType": 2,
            "content": "proton_027.jpg"
        },
        {
            "blockType": 2,
            "content": "proton_028.jpg"
        },
        {
            "blockType": 2,
            "content": "proton_029.jpg"
        },
        {
            "blockType": 2,
            "content": "proton_030.jpg"
        },
        {
            "blockType": 2,
            "content": "proton_031.jpg"
        },
        {
            "blockType": 2,
            "content": "proton_032.jpg"
        },
        {
            "blockType": 2,
            "content": "proton_033.jpg"
        },
        {
            "blockType": 2,
            "content": "proton_034.jpg"
        },
        {
            "blockType": 2,
            "content": "proton_035.jpg"
        },
        {
            "blockType": 2,
            "content": "proton_036.jpg"
        },
        {
            "blockType": 2,
            "content": "proton_037.jpg"
        },
        {
            "blockType": 2,
            "content": "proton_038.jpg"
        },
        {
            "blockType": 2,
            "content": "proton_039.jpg"
        },
        {
            "blockType": 2,
            "content": "proton_040.jpg"
        },
        {
            "blockType": 2,
            "content": "proton_041.jpg"
        },
        {
            "blockType": 2,
            "content": "proton_042.jpg"
        },
        {
            "blockType": 2,
            "content": "proton_043.jpg"
        },
        {
            "blockType": 2,
            "content": "proton_044.jpg"
        },
        {
            "blockType": 2,
            "content": "proton_045.jpg"
        },
        {
            "blockType": 2,
            "content": "proton_046.jpg"
        },
        {
            "blockType": 2,
            "content": "proton_047.jpg"
        },
        {
            "blockType": 2,
            "content": "proton_048.jpg"
        },
        {
            "blockType": 2,
            "content": "proton_049.jpg"
        },
        {
            "blockType": 2,
            "content": "proton_050.jpg"
        },
        {
            "blockType": 2,
            "content": "proton_051.jpg"
        },
        {
            "blockType": 2,
            "content": "proton_052.jpg"
        },
        {
            "blockType": 2,
            "content": "proton_053.jpg"
        },
        {
            "blockType": 2,
            "content": "proton_054.jpg"
        },
        {
            "blockType": 2,
            "content": "proton_055.jpg"
        },
        {
            "blockType": 2,
            "content": "proton_056.jpg"
        },
        {
            "blockType": 2,
            "content": "proton_057.jpg"
        },
        {
            "blockType": 2,
            "content": "proton_058.jpg"
        },
        {
            "blockType": 2,
            "content": "proton_059.jpg"
        },
        {
            "blockType": 2,
            "content": "proton_060.jpg"
        }
    ],
    "tags": [
        "hobby"
    ]
}